hallelujah/__init__.py
hallelujah/algorithm.py
hallelujah/app.py
hallelujah/applogger.py
hallelujah/batch.py
hallelujah/parser.py
hallelujah/test.py
hallelujah/utils.py
hallelujah-0.0.2.dist-info/licenses/LICENSE
hallelujah-0.0.2.dist-info/METADATA
hallelujah-0.0.2.dist-info/WHEEL
hallelujah-0.0.2.dist-info/entry_points.txt
hallelujah-0.0.2.dist-info/top_level.txt
hallelujah-0.0.2.dist-info/RECORD
